LICENSE
MANIFEST.in
README.md
setup.py
loranode/__init__.py
loranode/commands.py
loranode/loranode.py
loranode/rpyutils.py
loranode.egg-info/PKG-INFO
loranode.egg-info/SOURCES.txt
loranode.egg-info/dependency_links.txt
loranode.egg-info/requires.txt
loranode.egg-info/top_level.txt