Metadata-Version: 1.1
Name: loranode
Version: 0.0.4
Summary: Python 3 bindings for interfacing with LoRa nodes such as the RN2483.
Home-page: https://github.com/rpp0/python-loranode
Author: Pieter Robyns
Author-email: pieter.robyns@uhasselt.be
License: BSD License
Keywords: lora node modem serial interface
Platform: UNKNOWN
Classifier: Development Status :: 3 - Alpha
Classifier: Intended Audience :: Developers
Classifier: Topic :: Communications :: Ham Radio
Classifier: License :: OSI Approved :: BSD License
Classifier: Programming Language :: Python :: 3
Classifier: Programming Language :: Python :: 3.3
Classifier: Programming Language :: Python :: 3.4
Classifier: Programming Language :: Python :: 3.5
